ApacheFlume190ZhongwenWendang/README.md
ApacheFlume190ZhongwenWendang/__init__.py
ApacheFlume190ZhongwenWendang/__main__.py
ApacheFlume190ZhongwenWendang/file.epub
ApacheFlume190ZhongwenWendang/index.html
ApacheFlume190ZhongwenWendang/css/__init__.py
ApacheFlume190ZhongwenWendang/css/annotations.css
ApacheFlume190ZhongwenWendang/css/main.css
ApacheFlume190ZhongwenWendang/css/normalize.css
ApacheFlume190ZhongwenWendang/css/popup.css
ApacheFlume190ZhongwenWendang/font/__init__.py
ApacheFlume190ZhongwenWendang/font/fontello.eot
ApacheFlume190ZhongwenWendang/font/fontello.svg
ApacheFlume190ZhongwenWendang/font/fontello.ttf
ApacheFlume190ZhongwenWendang/font/fontello.woff
ApacheFlume190ZhongwenWendang/img/__init__.py
ApacheFlume190ZhongwenWendang/img/annotator-glyph-sprite.png
ApacheFlume190ZhongwenWendang/img/annotator-icon-sprite.png
ApacheFlume190ZhongwenWendang/img/apple-touch-icon.png
ApacheFlume190ZhongwenWendang/img/cancelfullscreen.png
ApacheFlume190ZhongwenWendang/img/close.png
ApacheFlume190ZhongwenWendang/img/fullscreen.png
ApacheFlume190ZhongwenWendang/img/loader.gif
ApacheFlume190ZhongwenWendang/img/menu-icon.png
ApacheFlume190ZhongwenWendang/img/save.png
ApacheFlume190ZhongwenWendang/img/saved.png
ApacheFlume190ZhongwenWendang/img/settings-s.png
ApacheFlume190ZhongwenWendang/img/settings.png
ApacheFlume190ZhongwenWendang/img/star.png
ApacheFlume190ZhongwenWendang/js/__init__.py
ApacheFlume190ZhongwenWendang/js/epub.js
ApacheFlume190ZhongwenWendang/js/epub.min.js
ApacheFlume190ZhongwenWendang/js/epub.min.map
ApacheFlume190ZhongwenWendang/js/hooks.min.js
ApacheFlume190ZhongwenWendang/js/hooks.min.map
ApacheFlume190ZhongwenWendang/js/reader.js
ApacheFlume190ZhongwenWendang/js/reader.js.map
ApacheFlume190ZhongwenWendang/js/reader.min.js
ApacheFlume190ZhongwenWendang/js/reader.min.map
ApacheFlume190ZhongwenWendang/js/hooks/__init__.py
ApacheFlume190ZhongwenWendang/js/hooks/extensions/__init__.py
ApacheFlume190ZhongwenWendang/js/hooks/extensions/highlight.js
apache_flume_1_9_0_zhongwen_wendang-2024.3.4.0.dist-info/METADATA
apache_flume_1_9_0_zhongwen_wendang-2024.3.4.0.dist-info/WHEEL
apache_flume_1_9_0_zhongwen_wendang-2024.3.4.0.dist-info/entry_points.txt
apache_flume_1_9_0_zhongwen_wendang-2024.3.4.0.dist-info/top_level.txt
apache_flume_1_9_0_zhongwen_wendang-2024.3.4.0.dist-info/RECORD
